pydanql/__init__.py
pydanql/base.py
pydanql/errors.py
pydanql/model.py
pydanql/table.py
pydanql-0.22.dist-info/LICENSE
pydanql-0.22.dist-info/METADATA
pydanql-0.22.dist-info/WHEEL
pydanql-0.22.dist-info/top_level.txt
pydanql-0.22.dist-info/RECORD
