Metadata-Version: 2.1
Name: pydanql
Version: 0.22
Home-page: https://blacktre.es
Author: Daniel Nümm
Author-email: pydanql@blacktre.es
Classifier: Programming Language :: Python :: 3
Classifier: License :: OSI Approved :: MIT License
Classifier: Operating System :: OS Independent
Classifier: Intended Audience :: Developers
Classifier: Topic :: Utilities
License-File: LICENSE
Requires-Dist: psycopg2-binary
Requires-Dist: pydantic
